databases_extensions-0.0.1.data/data/LICENSE.md
extensions/__init__.py
extensions/exceptions.py
extensions/pagination.py
extensions/query_builder.py
extensions/types.py
extensions/utils.py
databases_extensions-0.0.1.dist-info/LICENSE.md
databases_extensions-0.0.1.dist-info/METADATA
databases_extensions-0.0.1.dist-info/WHEEL
databases_extensions-0.0.1.dist-info/top_level.txt
databases_extensions-0.0.1.dist-info/RECORD
