Metadata-Version: 2.1
Name: databases-extensions
Version: 0.0.1
Summary: Extensions for sqlalchemy with databases
Home-page: https://github.com/chapagainmanoj/databases-query-extension
Author: Manoj Chapagain
Author-email: chapagainmanoj35@gmail.com
License: BSD
Platform: UNKNOWN
Classifier: Development Status :: 3 - Alpha
Classifier: Environment :: Web Environment
Classifier: Intended Audience :: Developers
Classifier: License :: OSI Approved :: BSD License
Classifier: Operating System :: OS Independent
Classifier: Topic :: Internet :: WWW/HTTP
Classifier: Programming Language :: Python :: 3
Classifier: Programming Language :: Python :: 3.6
Classifier: Programming Language :: Python :: 3.7
Classifier: Programming Language :: Python :: 3.8
Requires-Python: >=3.6
Requires-Dist: databases
Requires-Dist: pydantic
